pymudclient/__init__.py
pymudclient/configs.py
pymudclient/display.py
pymudclient/export_classes.py
pymudclient/input_processor.py
pymudclient/mud.py
pymudclient/recv_processor.py
pymudclient/shared_data.py
pymudclient/timer_processor.py
pymudclient/utils/__init__.py
pymudclient/utils/codec.py
pymudclient/utils/colors.py
pymudclient/utils/kbhit.py
pymudclient/utils/print.py
pymudclient/utils/telnet.py
pymudclient/utils/thread_safe.py
pymudclient-1.0.3.dist-info/LICENSE
pymudclient-1.0.3.dist-info/METADATA
pymudclient-1.0.3.dist-info/WHEEL
pymudclient-1.0.3.dist-info/top_level.txt
pymudclient-1.0.3.dist-info/RECORD
