Metadata-Version: 2.1
Name: pymudclient
Version: 1.0.3
Summary: A MUD client core written in Python
Home-page: https://github.com/griiid/PyMudClient
Download-URL: https://pypi.org/project/pymudclient/
Author: griiid
Author-email: gridwing@gmail.com
License: MIT
Classifier: Programming Language :: Python :: 3.7
Classifier: Programming Language :: Python :: 3.8
Classifier: Programming Language :: Python :: 3.9
Classifier: Programming Language :: Python :: 3.10
Classifier: Programming Language :: Python :: 3.11
Classifier: Programming Language :: Python :: 3.12
Requires-Python: >=3.7
License-File: LICENSE
Requires-Dist: Exscript==2.6.28
Provides-Extra: dev
Requires-Dist: python-dotenv==0.20.0; extra == "dev"
Requires-Dist: toml==0.10.2; extra == "dev"
Requires-Dist: yapf==0.40.1; extra == "dev"
